{
  "collectionName": "components_portfolio_page_categories",
  "info": {
    "displayName": "Category",
    "icon": "briefcase",
    "description": ""
  },
  "options": {},
  "attributes": {
    "title": {
      "type": "string",
      "required": true
    },
    "caption": {
      "type": "blocks"
    },
    "slug": {
      "type": "string",
      "required": true,
      "unique": true
    },
    "caseStudies": {
      "type": "relation",
      "relation": "oneToMany",
      "target": "api::case-study.case-study"
    }
  }
}
